<?xml version="1.0"?>
<!--Generated with glade3 3.4.5 on Mon Oct 12 11:24:33 2009 -->
<interface>
  <object class="GtkUIManager" id="uimanager1">
    <child>
      <object class="GtkActionGroup" id="actiongroup1">
        <child>
          <object class="GtkAction" id="menuitem1">
            <property name="name">menuitem1</property>
            <property name="label" translatable="yes">_File</property>
          </object>
        </child>
        <child>
          <object class="GtkAction" id="mnuSettings">
            <property name="name">mnuSettings</property>
            <property name="label" translatable="yes">_Settings</property>
          </object>
        </child>
        <child>
          <object class="GtkAction" id="mnuExit">
            <property name="name">mnuExit</property>
            <property name="label" translatable="yes">_Exit</property>
          </object>
        </child>
        <child>
          <object class="GtkAction" id="menuitem4">
            <property name="name">menuitem4</property>
            <property name="label" translatable="yes">_Help</property>
          </object>
        </child>
        <child>
          <object class="GtkAction" id="mnuAbout">
            <property name="stock_id" translatable="yes">gtk-about</property>
            <property name="name">mnuAbout</property>
          </object>
        </child>
      </object>
    </child>
    <ui>
      <menubar name="menubar1">
        <menu action="menuitem1">
          <menuitem action="mnuSettings"/>
          <separator/>
          <menuitem action="mnuExit"/>
        </menu>
        <menu action="menuitem4">
          <menuitem action="mnuAbout"/>
        </menu>
      </menubar>
    </ui>
  </object>
  <object class="GtkWindow" id="window1">
    <property name="title" translatable="yes">Web Watch</property>
    <property name="resizable">False</property>
    <property name="window_position">GTK_WIN_POS_CENTER</property>
    <child>
      <object class="GtkVBox" id="vbox1">
        <property name="visible">True</property>
        <child>
          <object class="GtkMenuBar" constructor="uimanager1" id="menubar1">
            <property name="visible">True</property>
          </object>
          <packing>
            <property name="expand">False</property>
          </packing>
        </child>
        <child>
          <object class="GtkHBox" id="hbox1">
            <property name="visible">True</property>
            <child>
              <object class="GtkImage" id="image">
                <property name="visible">True</property>
                <property name="stock">gtk-missing-image</property>
              </object>
            </child>
            <child>
              <object class="GtkVBox" id="vbox2">
                <property name="visible">True</property>
                <child>
                  <object class="GtkLabel" id="label1">
                    <property name="visible">True</property>
                    <property name="label" translatable="yes">

Next Update</property>
                  </object>
                  <packing>
                    <property name="expand">False</property>
                    <property name="fill">False</property>
                  </packing>
                </child>
                <child>
                  <object class="GtkVBox" id="vbox4">
                    <property name="visible">True</property>
                    <child>
                      <object class="GtkLabel" id="lblUpdate">
                        <property name="visible">True</property>
                        <property name="label" translatable="yes">Stopped</property>
                      </object>
                    </child>
                    <child>
                      <object class="GtkLabel" id="label3">
                        <property name="visible">True</property>
                        <property name="label" translatable="yes">

</property>
                      </object>
                      <packing>
                        <property name="position">1</property>
                      </packing>
                    </child>
                  </object>
                  <packing>
                    <property name="position">1</property>
                  </packing>
                </child>
                <child>
                  <object class="GtkVBox" id="vbox3">
                    <property name="visible">True</property>
                    <child>
                      <object class="GtkHButtonBox" id="hbuttonbox1">
                        <property name="visible">True</property>
                        <property name="layout_style">GTK_BUTTONBOX_CENTER</property>
                        <child>
                          <object class="GtkButton" id="btnStart">
                            <property name="visible">True</property>
                            <property name="can_focus">True</property>
                            <property name="receives_default">True</property>
                            <property name="label" translatable="yes">gtk-media-play</property>
                            <property name="use_stock">True</property>
                            <property name="image_position">GTK_POS_TOP</property>
                          </object>
                        </child>
                        <child>
                          <object class="GtkButton" id="btnStop">
                            <property name="visible">True</property>
                            <property name="can_focus">True</property>
                            <property name="receives_default">True</property>
                            <property name="label" translatable="yes">gtk-stop</property>
                            <property name="use_stock">True</property>
                            <property name="image_position">GTK_POS_TOP</property>
                          </object>
                          <packing>
                            <property name="position">1</property>
                          </packing>
                        </child>
                      </object>
                      <packing>
                        <property name="expand">False</property>
                        <property name="fill">False</property>
                      </packing>
                    </child>
                    <child>
                      <object class="GtkLinkButton" id="lbOpenWebPage">
                        <property name="visible">True</property>
                        <property name="can_focus">True</property>
                        <property name="receives_default">True</property>
                        <property name="has_tooltip">True</property>
                        <property name="label" translatable="yes">Open Web Page</property>
                        <property name="relief">GTK_RELIEF_NONE</property>
                        <property name="uri">http://glade.gnome.org</property>
                      </object>
                      <packing>
                        <property name="position">1</property>
                      </packing>
                    </child>
                  </object>
                  <packing>
                    <property name="position">2</property>
                  </packing>
                </child>
              </object>
              <packing>
                <property name="position">1</property>
              </packing>
            </child>
          </object>
          <packing>
            <property name="position">1</property>
          </packing>
        </child>
        <child>
          <object class="GtkHButtonBox" id="btnUpdateNow">
            <property name="visible">True</property>
            <property name="layout_style">GTK_BUTTONBOX_CENTER</property>
            <child>
              <object class="GtkButton" id="btnRefresh">
                <property name="visible">True</property>
                <property name="can_focus">True</property>
                <property name="receives_default">True</property>
                <property name="label" translatable="yes">gtk-refresh</property>
                <property name="use_stock">True</property>
                <signal handler="on_button1_clicked" name="clicked"/>
              </object>
              <packing>
                <property name="expand">False</property>
                <property name="fill">False</property>
                <property name="pack_type">GTK_PACK_END</property>
              </packing>
            </child>
          </object>
          <packing>
            <property name="expand">False</property>
            <property name="pack_type">GTK_PACK_END</property>
            <property name="position">2</property>
          </packing>
        </child>
      </object>
    </child>
  </object>
</interface>
